iacs_ipac_reader/ApplyRF.py
iacs_ipac_reader/MANIFEST.in
iacs_ipac_reader/__init__.py
iacs_ipac_reader/_dock_widget.py
iacs_ipac_reader/aid_cv2_dnn.py
iacs_ipac_reader/background_program.py
iacs_ipac_reader/image_processing.py
iacs_ipac_reader/_tests/__init__.py
iacs_ipac_reader/_tests/test_dock_widget.py
iacs_ipac_reader/art/aqua.png
iacs_ipac_reader/art/black.png
iacs_ipac_reader/art/delete.png
iacs_ipac_reader/art/eye.png
iacs_ipac_reader/art/green.png
iacs_ipac_reader/art/red.png
iacs_ipac_reader/art/visibility_off.png
iacs_ipac_reader/art/white.png
iacs_ipac_reader-0.0.13.dist-info/LICENSE
iacs_ipac_reader-0.0.13.dist-info/METADATA
iacs_ipac_reader-0.0.13.dist-info/WHEEL
iacs_ipac_reader-0.0.13.dist-info/entry_points.txt
iacs_ipac_reader-0.0.13.dist-info/top_level.txt
iacs_ipac_reader-0.0.13.dist-info/RECORD
