Metadata-Version: 2.1
Name: iacs-ipac-reader
Version: 0.0.13
Summary: A reader plugin for read iacs/ipac images and export .rtdc files.
Home-page: https://github.com/zcqwh/iacs_ipac_reader
Author: Chenqi Zhang
Author-email: cqzhang@g.ecc.u-tokyo.ac.jp
License: BSD-3-Clause
Project-URL: Bug Tracker, https://github.com/zcqwh/iacs_ipac_reader/issues
Project-URL: Documentation, https://github.com/zcqwh/iacs_ipac_reader#README.md
Project-URL: Source Code, https://github.com/zcqwh/iacs_ipac_reader
Project-URL: User Support, https://github.com/zcqwh/iacs_ipac_reader/issues
Platform: UNKNOWN
Classifier: Development Status :: 2 - Pre-Alpha
Classifier: Intended Audience :: Developers
Classifier: Framework :: napari
Classifier: Topic :: Software Development :: Testing
Classifier: Programming Language :: Python
Classifier: Programming Language :: Python :: 3
Classifier: Programming Language :: Python :: 3.7
Classifier: Programming Language :: Python :: 3.8
Classifier: Programming Language :: Python :: 3.9
Classifier: Operating System :: OS Independent
Classifier: License :: OSI Approved :: BSD License
Requires-Python: >=3.7
License-File: LICENSE
Requires-Dist: h5py (>=3.5.0)
Requires-Dist: napari (>=0.4.12)
Requires-Dist: napari-plugin-engine (>=0.2.0)
Requires-Dist: numpy (>=1.21.4)
Requires-Dist: opencv-contrib-python-headless (>=4.4.0.46)
Requires-Dist: openpyxl (>=3.0.9)
Requires-Dist: sklearn (>=0.0)
Requires-Dist: PyQt5 (==5.12.3)
Requires-Dist: pandas (>=1.4.0)
